pyntnclick/__init__.py
pyntnclick/constants.py
pyntnclick/cursor.py
pyntnclick/engine.py
pyntnclick/gamescreen.py
pyntnclick/i18n.py
pyntnclick/image_transforms.py
pyntnclick/main.py
pyntnclick/menuscreen.py
pyntnclick/resources.py
pyntnclick/scenewidgets.py
pyntnclick/sound.py
pyntnclick/speech.py
pyntnclick/state.py
pyntnclick/utils.py
pyntnclick/version.py
pyntnclick/data/__init__.py
pyntnclick/data/images/pyntnclick/end.png
pyntnclick/data/images/pyntnclick/hand.png
pyntnclick/data/images/pyntnclick/start.png
pyntnclick/data/locale/af/LC_MESSAGES/pyntnclick-tools.mo
pyntnclick/data/po/af.po
pyntnclick/data/po/pyntnclick-tools.pot
pyntnclick/tests/__init__.py
pyntnclick/tests/game_logic_utils.py
pyntnclick/tests/mad_clicker.py
pyntnclick/tests/test_resources.py
pyntnclick/tools/__init__.py
pyntnclick/tools/gen_sound.py
pyntnclick/tools/rect_drawer.py
pyntnclick/widgets/__init__.py
pyntnclick/widgets/base.py
pyntnclick/widgets/filechooser.py
pyntnclick/widgets/imagebutton.py
pyntnclick/widgets/text.py
pyntnclick/widgets/toollist.py
Pyntnclick-0.0.1.dist-info/COPYING
Pyntnclick-0.0.1.dist-info/METADATA
Pyntnclick-0.0.1.dist-info/WHEEL
Pyntnclick-0.0.1.dist-info/top_level.txt
Pyntnclick-0.0.1.dist-info/RECORD
